azure/__init__.py
azure/cli/__init__.py
azure/cli/telemetry/__init__.py
azure/cli/telemetry/const.py
azure/cli/telemetry/util.py
azure/cli/telemetry/components/__init__.py
azure/cli/telemetry/components/records_collection.py
azure/cli/telemetry/components/telemetry_client.py
azure/cli/telemetry/components/telemetry_logging.py
azure/cli/telemetry/components/telemetry_note.py
opal_azure_cli_telemetry-1.0.4.dist-info/METADATA
opal_azure_cli_telemetry-1.0.4.dist-info/WHEEL
opal_azure_cli_telemetry-1.0.4.dist-info/top_level.txt
opal_azure_cli_telemetry-1.0.4.dist-info/RECORD
