Metadata-Version: 2.1
Name: opal-azure-cli-telemetry
Version: 1.0.4
Summary: Microsoft Azure CLI Telemetry Package
Home-page: https://github.com/Azure/azure-cli
Author: Microsoft Corporation
Author-email: azpycli@microsoft.com
License: MIT
Platform: UNKNOWN
Classifier: Development Status :: 5 - Production/Stable
Classifier: Intended Audience :: Developers
Classifier: Intended Audience :: System Administrators
Classifier: Programming Language :: Python
Classifier: Programming Language :: Python :: 2
Classifier: Programming Language :: Python :: 2.7
Classifier: Programming Language :: Python :: 3
Classifier: Programming Language :: Python :: 3.4
Classifier: Programming Language :: Python :: 3.5
Classifier: Programming Language :: Python :: 3.6
Classifier: License :: OSI Approved :: MIT License
Requires-Dist: applicationinsights (<0.12,>=0.11.1)
Requires-Dist: portalocker (~=1.2)
Requires-Dist: azure-cli-nspkg (>=2.0.0)
